matterdelta/__init__.py
matterdelta/__main__.py
matterdelta/_version.py
matterdelta/api.py
matterdelta/hooks.py
matterdelta-1.6.3.dist-info/LICENSE.txt
matterdelta-1.6.3.dist-info/METADATA
matterdelta-1.6.3.dist-info/WHEEL
matterdelta-1.6.3.dist-info/entry_points.txt
matterdelta-1.6.3.dist-info/top_level.txt
matterdelta-1.6.3.dist-info/RECORD
