Metadata-Version: 2.2
Name: matterdelta
Version: 1.6.3
Summary: Matterbridge API plugin for Delta Chat
Author-email: adbenitez <adb@merlinux.eu>
Project-URL: Homepage, https://github.com/deltachat-bot/matterdelta
Keywords: deltachat,bot,matterbridge,bridge
Classifier: Development Status :: 4 - Beta
Classifier: Programming Language :: Python
Classifier: License :: OSI Approved :: GNU General Public License v3 or later (GPLv3+)
Requires-Python: >=3.8
License-File: LICENSE.txt
Requires-Dist: deltabot-cli<7.0,>=6.1.0
Requires-Dist: requests
Provides-Extra: fast
Requires-Dist: cchardet>=2.1.7; extra == "fast"
Provides-Extra: dev
Requires-Dist: black; extra == "dev"
Requires-Dist: mypy; extra == "dev"
Requires-Dist: isort; extra == "dev"
Requires-Dist: pylint; extra == "dev"
Requires-Dist: pylama; extra == "dev"
Requires-Dist: pytest; extra == "dev"
Requires-Dist: types-requests; extra == "dev"
